PyMediaRSS2Gen.py
PyMediaRSS2Gen-0.1.0.dist-info/DESCRIPTION.rst
PyMediaRSS2Gen-0.1.0.dist-info/METADATA
PyMediaRSS2Gen-0.1.0.dist-info/metadata.json
PyMediaRSS2Gen-0.1.0.dist-info/RECORD
PyMediaRSS2Gen-0.1.0.dist-info/top_level.txt
PyMediaRSS2Gen-0.1.0.dist-info/WHEEL
