Metadata-Version: 2.0
Name: PyMediaRSS2Gen
Version: 0.1.0
Summary: A Python library for generating Media RSS 2.0 feeds.
Home-page: https://github.com/wedi/PyMediaRSS2Gen
Author: Dirk Weise
Author-email: code@dirk-weise.de
License: MIT
Download-URL: https://github.com/wedi/PyMediaRSS2Gen/archive/v0.1.0.tar.gz
Keywords: RSS,Feed
Platform: UNKNOWN
Classifier: Programming Language :: Python
Classifier: Programming Language :: Python :: 2
Classifier: Programming Language :: Python :: 2.6
Classifier: Programming Language :: Python :: 2.7
Classifier: Programming Language :: Python :: 3
Classifier: Programming Language :: Python :: 3.4
Classifier: Development Status :: 3 - Alpha
Classifier: Environment :: Web Environment
Classifier: Intended Audience :: Developers
Classifier: License :: OSI Approved :: MIT License
Classifier: Operating System :: OS Independent
Classifier: Topic :: Internet :: WWW/HTTP
Classifier: Topic :: Software Development :: Libraries :: Python Modules
Classifier: Topic :: Text Processing :: Markup :: XML
